{
	"configurations" : 
	[
		{
			"directories" : 
			[
				{
					"build" : ".",
					"jsonFile" : "directory-.-Debug-f5ebdc15457944623624.json",
					"minimumCMakeVersion" : 
					{
						"string" : "3.6.0"
					},
					"projectIndex" : 0,
					"source" : ".",
					"targetIndexes" : 
					[
						0
					]
				}
			],
			"name" : "Debug",
			"projects" : 
			[
				{
					"directoryIndexes" : 
					[
						0
					],
					"name" : "packethunter",
					"targetIndexes" : 
					[
						0
					]
				}
			],
			"targets" : 
			[
				{
					"directoryIndex" : 0,
					"id" : "packethunter::@6890427a1f51a3e7e1df",
					"jsonFile" : "target-packethunter-Debug-34b81c3c5e2b34e1793f.json",
					"name" : "packethunter",
					"projectIndex" : 0
				}
			]
		}
	],
	"kind" : "codemodel",
	"paths" : 
	{
		"build" : "/Users/prasham/Desktop/Cursor-MPH/mobile-packet-hunter/android-app/app/.cxx/Debug/5k6b526g/x86",
		"source" : "/Users/prasham/Desktop/Cursor-MPH/mobile-packet-hunter/android-app/app/src/main/cpp"
	},
	"version" : 
	{
		"major" : 2,
		"minor" : 3
	}
}
